<?xml version="1.0" encoding="utf-8"?>
<hops>
<hop>
<name>Admiral</name>
<alpha>14.7500000</alpha>
</hop>
<hop>
<name>Ahtanum</name>
<alpha>6.0000000</alpha>
</hop>
<hop>
<name>Amarillo Gold</name>
<alpha>8.5000000</alpha>
</hop>
<hop>
<name>Apollo</name>
<alpha>17.0000000</alpha>
</hop>
<hop>
<name>Aquila</name>
<alpha>6.5000000</alpha>
</hop>
<hop>
<name>Atlas</name>
<alpha>9.0000000</alpha>
</hop>
<hop>
<name>Aurora</name>
<alpha>8.2500000</alpha>
</hop>
<hop>
<name>Banner</name>
<alpha>10.0000000</alpha>
</hop>
<hop>
<name>Bobek</name>
<alpha>5.2500000</alpha>
</hop>
<hop>
<name>Bramling Cross</name>
<alpha>6.0000000</alpha>
</hop>
<hop>
<name>Bravo</name>
<alpha>15.5000000</alpha>
</hop>
<hop>
<name>Brewer's Gold</name>
<alpha>8.0000000</alpha>
</hop>
<hop>
<name>Bullion</name>
<alpha>8.0000000</alpha>
</hop>
<hop>
<name>Cascade</name>
<alpha>5.5000000</alpha>
</hop>
<hop>
<name>Celeia</name>
<alpha>4.5000000</alpha>
</hop>
<hop>
<name>Centennial</name>
<alpha>10.0000000</alpha>
</hop>
<hop>
<name>Challenger</name>
<alpha>7.5000000</alpha>
</hop>
<hop>
<name>Chelan</name>
<alpha>13.2500000</alpha>
</hop>
<hop>
<name>Chinook</name>
<alpha>13.0000000</alpha>
</hop>
<hop>
<name>Citra</name>
<alpha>12.0000000</alpha>
</hop>
<hop>
<name>Cluster</name>
<alpha>7.0000000</alpha>
</hop>
<hop>
<name>Columbia</name>
<alpha>5.5000000</alpha>
</hop>
<hop>
<name>Columbus (Tomahawk)</name>
<alpha>14.0000000</alpha>
</hop>
<hop>
<name>Comet</name>
<alpha>9.5000000</alpha>
</hop>
<hop>
<name>Crystal</name>
<alpha>3.5000000</alpha>
</hop>
<hop>
<name>Eroica</name>
<alpha>13.0000000</alpha>
</hop>
<hop>
<name>Feux Coeur Francais</name>
<alpha>14.0000000</alpha>
</hop>
<hop>
<name>First Gold</name>
<alpha>7.5000000</alpha>
</hop>
<hop>
<name>Fuggles</name>
<alpha>4.5000000</alpha>
</hop>
<hop>
<name>Galaxy</name>
<alpha>14.0000000</alpha>
</hop>
<hop>
<name>Galena</name>
<alpha>12.5000000</alpha>
</hop>
<hop>
<name>Glacier</name>
<alpha>5.6000000</alpha>
</hop>
<hop>
<name>Goldings, B.C.</name>
<alpha>5.0000000</alpha>
</hop>
<hop>
<name>Goldings, East Kent</name>
<alpha>5.0000000</alpha>
</hop>
<hop>
<name>Green Bullet</name>
<alpha>13.5000000</alpha>
</hop>
<hop>
<name>Greenburg</name>
<alpha>5.2000000</alpha>
</hop>
<hop>
<name>Hallertauer</name>
<alpha>4.8000000</alpha>
</hop>
<hop>
<name>Hallertauer Hersbrucker</name>
<alpha>4.0000000</alpha>
</hop>
<hop>
<name>Hallertauer Mittelfrueh</name>
<alpha>4.0000000</alpha>
</hop>
<hop>
<name>Hallertauer, New Zealand</name>
<alpha>8.5000000</alpha>
</hop>
<hop>
<name>Herald</name>
<alpha>12.0000000</alpha>
</hop>
<hop>
<name>Horizon</name>
<alpha>12.0000000</alpha>
</hop>
<hop>
<name>Liberty</name>
<alpha>4.3000000</alpha>
</hop>
<hop>
<name>Lublin</name>
<alpha>5.0000000</alpha>
</hop>
<hop>
<name>Magnum</name>
<alpha>14.0000000</alpha>
</hop>
<hop>
<name>Marynka</name>
<alpha>10.5000000</alpha>
</hop>
<hop>
<name>Millenium</name>
<alpha>14.2500000</alpha>
</hop>
<hop>
<name>Motueka</name>
<alpha>7.0000000</alpha>
</hop>
<hop>
<name>Mt. Hood</name>
<alpha>6.0000000</alpha>
</hop>
<hop>
<name>Nelson Sauvin</name>
<alpha>12.0000000</alpha>
</hop>
<hop>
<name>Newport</name>
<alpha>13.5000000</alpha>
</hop>
<hop>
<name>Northdown</name>
<alpha>8.5000000</alpha>
</hop>
<hop>
<name>Northern Brewer</name>
<alpha>8.5000000</alpha>
</hop>
<hop>
<name>Nugget</name>
<alpha>13.0000000</alpha>
</hop>
<hop>
<name>Olympic</name>
<alpha>11.5000000</alpha>
</hop>
<hop>
<name>Opal</name>
<alpha>6.5000000</alpha>
</hop>
<hop>
<name>Orion</name>
<alpha>7.2500000</alpha>
</hop>
<hop>
<name>Pacific Gem</name>
<alpha>15.0000000</alpha>
</hop>
<hop>
<name>Pacific Jade</name>
<alpha>13.0000000</alpha>
</hop>
<hop>
<name>Pacifica</name>
<alpha>5.5000000</alpha>
</hop>
<hop>
<name>Palisade</name>
<alpha>7.5000000</alpha>
</hop>
<hop>
<name>Perle</name>
<alpha>8.0000000</alpha>
</hop>
<hop>
<name>Phoenix</name>
<alpha>8.0000000</alpha>
</hop>
<hop>
<name>Pilgrim</name>
<alpha>11.5000000</alpha>
</hop>
<hop>
<name>Pilot</name>
<alpha>11.5000000</alpha>
</hop>
<hop>
<name>Pioneer</name>
<alpha>9.0000000</alpha>
</hop>
<hop>
<name>Premiant</name>
<alpha>7.5000000</alpha>
</hop>
<hop>
<name>Pride of Ringwood</name>
<alpha>9.0000000</alpha>
</hop>
<hop>
<name>Progress</name>
<alpha>6.2500000</alpha>
</hop>
<hop>
<name>Riwaka</name>
<alpha>5.2500000</alpha>
</hop>
<hop>
<name>Saaz</name>
<alpha>4.0000000</alpha>
</hop>
<hop>
<name>Santiam</name>
<alpha>6.0000000</alpha>
</hop>
<hop>
<name>Saphir</name>
<alpha>3.5000000</alpha>
</hop>
<hop>
<name>Satus</name>
<alpha>13.2500000</alpha>
</hop>
<hop>
<name>Select Spalt</name>
<alpha>4.7500000</alpha>
</hop>
<hop>
<name>Simcoe</name>
<alpha>13.0000000</alpha>
</hop>
<hop>
<name>Sladek</name>
<alpha>5.0000000</alpha>
</hop>
<hop>
<name>Sorachi Ace</name>
<alpha>12.0000000</alpha>
</hop>
<hop>
<name>Southern Cross</name>
<alpha>13.0000000</alpha>
</hop>
<hop>
<name>Spalter</name>
<alpha>4.5000000</alpha>
</hop>
<hop>
<name>Sterling</name>
<alpha>7.5000000</alpha>
</hop>
<hop>
<name>Sticklebract</name>
<alpha>13.5000000</alpha>
</hop>
<hop>
<name>Strisslespalt</name>
<alpha>4.0000000</alpha>
</hop>
<hop>
<name>Styrian Goldings</name>
<alpha>5.4000000</alpha>
</hop>
<hop>
<name>Summit</name>
<alpha>17.0000000</alpha>
</hop>
<hop>
<name>Sun</name>
<alpha>14.0000000</alpha>
</hop>
<hop>
<name>Super Alpha</name>
<alpha>13.0000000</alpha>
</hop>
<hop>
<name>Super Galena</name>
<alpha>14.5000000</alpha>
</hop>
<hop>
<name>Super Pride</name>
<alpha>14.2500000</alpha>
</hop>
<hop>
<name>Target</name>
<alpha>11.0000000</alpha>
</hop>
<hop>
<name>Tettnang</name>
<alpha>4.5000000</alpha>
</hop>
<hop>
<name>Tillicum</name>
<alpha>13.2500000</alpha>
</hop>
<hop>
<name>Tomahawk</name>
<alpha>15.5000000</alpha>
</hop>
<hop>
<name>Topaz</name>
<alpha>17.0000000</alpha>
</hop>
<hop>
<name>Tradition</name>
<alpha>6.0000000</alpha>
</hop>
<hop>
<name>Ultra</name>
<alpha>3.0000000</alpha>
</hop>
<hop>
<name>Vanguard</name>
<alpha>5.5000000</alpha>
</hop>
<hop>
<name>Victoria</name>
<alpha>13.0000000</alpha>
</hop>
<hop>
<name>Warrior</name>
<alpha>15.0000000</alpha>
</hop>
<hop>
<name>Whitbread Golding Variety (WGV)</name>
<alpha>6.0000000</alpha>
</hop>
<hop>
<name>Willamette</name>
<alpha>5.5000000</alpha>
</hop>
<hop>
<name>Zeus</name>
<alpha>14.0000000</alpha>
</hop>
</hops>
